DIRACWebAppResources
