Metadata-Version: 2.1
Name: DIRACWebAppResources
Version: 1.0.1
Summary: DIRACWebAppResources contains slowly changing assets for WebAppDIRAC
Home-page: https://github.com/DIRACGrid/DIRACWebAppResources/
License: GPL-3.0-only
Platform: UNKNOWN
Classifier: Development Status :: 5 - Production/Stable
Classifier: Intended Audience :: Science/Research
Classifier: License :: OSI Approved :: GNU General Public License v3 (GPLv3)
Classifier: Programming Language :: Python :: 3
Classifier: Topic :: Scientific/Engineering
Classifier: Topic :: System :: Distributed Computing
Requires-Python: >=3.9
License-File: LICENSE
